simpleSVGD/__init__.py
simpleSVGD/_version.py
simpleSVGD/helpers.py
simpleSVGD/kernels.py
simpleSVGD-0.3.dist-info/LICENSE
simpleSVGD-0.3.dist-info/METADATA
simpleSVGD-0.3.dist-info/WHEEL
simpleSVGD-0.3.dist-info/top_level.txt
simpleSVGD-0.3.dist-info/RECORD
