Metadata-Version: 2.1
Name: simpleSVGD
Version: 0.3
Summary: A very basic implementation of SVGD, based on https://github.com/dilinwang820/Stein-Variational-Gradient-Descent
Home-page: https://github.com/larsgeb/simpleSVGD
Author: Lars Gebraad
Author-email: lars.gebraad@erdw.ethz.ch
License: UNKNOWN
Project-URL: Bug Tracker, https://github.com/larsgeb/simpleSVGD/issues
Platform: UNKNOWN
Classifier: Development Status :: 4 - Beta
Classifier: Programming Language :: Python :: 3.7
Classifier: License :: OSI Approved :: BSD License
Classifier: Operating System :: OS Independent
Requires-Python: >=3.7
License-File: LICENSE
Requires-Dist: numpy
Requires-Dist: tqdm
Requires-Dist: scipy
Requires-Dist: matplotlib
Requires-Dist: versioneer
Provides-Extra: dev
Requires-Dist: black ; extra == 'dev'
Requires-Dist: pytest ; extra == 'dev'
